{
  "schema_version": 4,
  "fs": "zfs",
  "layout": "raidz1-enc",
  "kernel": "7.0.0-1009-azure",
  "version": "zfs-2.4.1-1ubuntu5 zfs-kmod-2.4.1-1ubuntu5",
  "date": "2026-07-22T10:43:33Z",
  "devices": "loop",
  "ndev": 4,
  "device_size_bytes": 2147483648,
  "calibration": {
    "seqwrite_mbps": 407.9681272506714,
    "randwrite_iops": 14726.824392
  },
  "results": {
    "seqwrite_mbps": 270.077805519104,
    "randwrite_iops": 2445.356001,
    "fsync_p99_ms": 105.381888,
    "fsync_p999_ms": 177.209344,
    "randread_iops": 11694.503926,
    "randread4_iops": 21011.862777,
    "seqread_mbps": 398.2886028289795,
    "lat_idle_p99_ms": 1.875968,
    "lat_load_p99_ms": null,
    "lat_load_max_ms": 1196.528233,
    "lat_load_ops": 12,
    "smalltree_create_ms": 1989,
    "smalltree_create4_ms": 952,
    "randwrite4_iops": 2506.044791,
    "smalltree_cp_ms": 1925,
    "smalltree_rm_ms": 863,
    "largedir_create_ms": 4114,
    "largedir_readdir_cold_ms": 135,
    "largedir_stat_cold_ms": 1781,
    "largedir_stat_warm_ms": 385,
    "largedir_delete_ms": 4505,
    "aging_mbps": [
      11.422451972961426,
      14.106237411499023,
      13.943354606628418,
      10.040790557861328,
      9.759072303771973,
      8.866721153259277,
      9.067724227905273,
      8.798460006713867,
      8.054366111755371,
      6.070378303527832
    ],
    "snapshot_create_ms": 550,
    "snapshot_delete_ms": 433,
    "reclaim_s": 11,
    "reclaim_write_mbps": 5.872097969055176,
    "reclaim_free_pct": 99.9956430938681,
    "compress_ratio": 3.87,
    "compress_write_mbps": 436.20873260498047,
    "sparse_create_ms": 26.317,
    "sparse_create_bytes": 512,
    "sparse_grow_ms": 1.489,
    "sparse_grow_bytes": 0,
    "reflink_ms": null,
    "reflink_fiemap_shared": null,
    "divergence_plain_mbps": 11.16051959991455,
    "divergence_clone_mbps": null,
    "divergence_snap_mbps": 10.168414115905762,
    "degraded_randwrite_iops": 2931.635612,
    "degraded_randread_iops": 42768.141062,
    "rebuild_s": 28,
    "snapscale_count": 500,
    "snapscale_create_ms": 16,
    "snapscale_total_s": 7,
    "snapscale_list_ms": 233,
    "snapscale_remount_ms": 1307,
    "snapscale_delete_ms": 2619,
    "nearfull95_write_mbps": 9.459059715270996,
    "nearfull99_write_mbps": 0,
    "nearfull95_pct": 1,
    "nearfull99_pct": 100,
    "enospc_delete_ok": true,
    "enospc_recover_ok": true,
    "scrub_s": 35,
    "scrub_found": 30496,
    "scrub_repaired": 30496,
    "data_intact": true
  }
}
