{
  "fs": "xfs",
  "layout": "lvm-raid10",
  "kernel": "7.0.0-1009-azure",
  "version": "mkfs.xfs version 6.18.0",
  "date": "2026-07-16T06:50:57Z",
  "devices": "loop",
  "ndev": 4,
  "calibration": {
    "seqwrite_mbps": 407.80565452575684,
    "randwrite_iops": 14801.226503
  },
  "results": {
    "seqwrite_mbps": 193.00725650787354,
    "randwrite_iops": 5744.683688,
    "fsync_p99_ms": 5.210112,
    "fsync_p999_ms": 8.159232,
    "randread_iops": 5456.558844,
    "randread4_iops": 18411.574659,
    "seqread_mbps": 377.58112049102783,
    "lat_idle_p99_ms": 2.572288,
    "lat_load_p99_ms": 54.263808,
    "lat_load_max_ms": 55.29858,
    "lat_load_ops": 138,
    "smalltree_create_ms": 2467,
    "smalltree_create4_ms": 1645,
    "randwrite4_iops": 3746.801706,
    "smalltree_cp_ms": 1696,
    "smalltree_rm_ms": 684,
    "aging_mbps": [
      33.04078388214111,
      33.50785255432129,
      32.95571517944336,
      32.669729232788086,
      32.938754081726074,
      33.701948165893555,
      32.306915283203125,
      32.68641376495361
    ],
    "snapshot_create_ms": 303,
    "snapshot_delete_ms": 2465,
    "reclaim_s": 4,
    "reclaim_write_mbps": 31.31115436553955,
    "compress_ratio": null,
    "compress_write_mbps": null,
    "sparse_create_ms": 13.688,
    "sparse_create_bytes": 0,
    "sparse_grow_ms": 0.521,
    "sparse_grow_bytes": 0,
    "reflink_ms": 4,
    "reflink_fiemap_shared": true,
    "divergence_plain_mbps": 33.42909336090088,
    "divergence_clone_mbps": 17.81241226196289,
    "divergence_snap_mbps": 34.744842529296875,
    "degraded_randwrite_iops": 5219.385374,
    "degraded_randread_iops": 5462.251258,
    "rebuild_s": 43,
    "snapscale_count": 150,
    "snapscale_create_ms": 3569,
    "snapscale_total_s": 297,
    "snapscale_list_ms": 41,
    "snapscale_remount_ms": 3577,
    "snapscale_delete_ms": 317236,
    "nearfull95_write_mbps": 86.48648643493652,
    "nearfull99_write_mbps": 67.58183670043945,
    "nearfull95_pct": 97,
    "nearfull99_pct": 100,
    "enospc_delete_ok": true,
    "enospc_recover_ok": true,
    "scrub_s": 84,
    "scrub_found": 4194304,
    "scrub_repaired": 0,
    "data_intact": false
  }
}
