{
  "schema_version": 5,
  "fs": "zfs",
  "layout": "raidz1",
  "kernel": "7.0.0-1009-azure",
  "version": "zfs-2.4.1-1ubuntu5 zfs-kmod-2.4.1-1ubuntu5",
  "date": "2026-07-23T22:23:08Z",
  "devices": "loop",
  "ndev": 4,
  "device_size_bytes": 2147483648,
  "calibration": {
    "seqwrite_mbps": 400.46929931640625,
    "randwrite_iops": 14757.416172
  },
  "results": {
    "seqwrite_mbps": 277.69491481781006,
    "randwrite_iops": 2643.246840,
    "fsync_p99_ms": 106.430464,
    "fsync_p999_ms": 173.01504,
    "randread_iops": 16425.062657,
    "randread4_iops": 20745.805635,
    "seqread_mbps": 401.41121101379395,
    "lat_idle_p99_ms": 1.400832,
    "lat_load_p99_ms": null,
    "lat_load_max_ms": 1535.018794,
    "lat_load_ops": 13,
    "smalltree_create_ms": 1016,
    "smalltree_create4_ms": 579,
    "randwrite4_iops": 2568.447467,
    "smalltree_cp_ms": 908,
    "smalltree_rm_ms": 390,
    "largedir_create_ms": 1727,
    "largedir_readdir_cold_ms": 85,
    "largedir_stat_cold_ms": 869,
    "largedir_stat_warm_ms": 250,
    "largedir_delete_ms": 2471,
    "aging_mbps": [
      12.075470924377441,
      12.817944526672363,
      12.688342094421387,
      14.244379997253418,
      10.349287986755371,
      10.042366027832031,
      10.500410079956055,
      9.705792427062988,
      9.945609092712402,
      8.239989280700684
    ],
    "snapshot_create_ms": 532,
    "snapshot_delete_ms": 753,
    "reclaim_s": 9,
    "reclaim_write_mbps": 7.658249855041504,
    "reclaim_free_pct": 99.99593367238761,
    "compress_ratio": 3.87,
    "compress_write_mbps": 458.6786108016968,
    "sparse_create_ms": 7.847,
    "sparse_create_bytes": 512,
    "sparse_grow_ms": 0.921,
    "sparse_grow_bytes": 0,
    "reflink_ms": 120,
    "reflink_fiemap_shared": false,
    "divergence_plain_mbps": 13.059891700744629,
    "divergence_clone_mbps": 7.231229782104492,
    "divergence_snap_mbps": 9.948701858520508,
    "degraded_randwrite_iops": 3046.131796,
    "degraded_randread_iops": 40048.098397,
    "rebuild_s": 34,
    "snapscale_count": 500,
    "snapscale_create_ms": 11,
    "snapscale_total_s": 5,
    "snapscale_list_ms": 96,
    "snapscale_remount_ms": 736,
    "snapscale_delete_ms": 1395,
    "nearfull95_write_mbps": 9.362199783325195,
    "nearfull99_write_mbps": 0,
    "nearfull95_pct": 1,
    "nearfull99_pct": 100,
    "enospc_delete_ok": true,
    "enospc_recover_ok": true,
    "scrub_s": 41,
    "scrub_found": 22186,
    "scrub_repaired": 22186,
    "data_intact": true
  }
}
