{
  "schema_version": 4,
  "fs": "zfs",
  "layout": "single",
  "kernel": "7.0.0-1009-azure",
  "version": "zfs-2.4.1-1ubuntu5 zfs-kmod-2.4.1-1ubuntu5",
  "date": "2026-07-21T03:51:59Z",
  "devices": "loop",
  "ndev": 4,
  "calibration": {
    "seqwrite_mbps": 395.51950550079346,
    "randwrite_iops": 14821.635287
  },
  "results": {
    "seqwrite_mbps": 375.7108783721924,
    "randwrite_iops": 3581.604449,
    "fsync_p99_ms": 49.545216,
    "fsync_p999_ms": 56.885248,
    "randread_iops": 15331.851679,
    "randread4_iops": 23039.550009,
    "seqread_mbps": 415.50010108947754,
    "lat_idle_p99_ms": 1.073152,
    "lat_load_p99_ms": 952.107008,
    "lat_load_max_ms": 950.831099,
    "lat_load_ops": 20,
    "smalltree_create_ms": 1030,
    "smalltree_create4_ms": 550,
    "randwrite4_iops": 3491.131257,
    "smalltree_cp_ms": 880,
    "smalltree_rm_ms": 392,
    "largedir_create_ms": 1707,
    "largedir_readdir_cold_ms": 78,
    "largedir_stat_cold_ms": 869,
    "largedir_stat_warm_ms": 252,
    "largedir_delete_ms": 2507,
    "aging_mbps": [
      18.03324794769287,
      18.109789848327637,
      17.927170753479004,
      17.862126350402832,
      17.777777671813965,
      19.801980018615723,
      15.697816848754883,
      13.710368156433105,
      13.272500991821289,
      13.201319694519043
    ],
    "snapshot_create_ms": 647,
    "snapshot_delete_ms": 187,
    "reclaim_s": 5,
    "reclaim_write_mbps": 14.038166046142578,
    "reclaim_free_pct": 99.99539577885005,
    "compress_ratio": 3.87,
    "compress_write_mbps": 485.4230852127075,
    "sparse_create_ms": 6.023,
    "sparse_create_bytes": 512,
    "sparse_grow_ms": 1.002,
    "sparse_grow_bytes": 0,
    "reflink_ms": null,
    "reflink_fiemap_shared": null,
    "divergence_plain_mbps": 17.280949592590332,
    "divergence_clone_mbps": null,
    "divergence_snap_mbps": 16.859851837158203,
    "degraded_randwrite_iops": null,
    "degraded_randread_iops": null,
    "rebuild_s": null,
    "snapscale_count": 500,
    "snapscale_create_ms": 10,
    "snapscale_total_s": 4,
    "snapscale_list_ms": 102,
    "snapscale_remount_ms": 473,
    "snapscale_delete_ms": 1382,
    "nearfull95_write_mbps": 11.918063163757324,
    "nearfull99_write_mbps": 0,
    "nearfull95_pct": 1,
    "nearfull99_pct": 100,
    "enospc_delete_ok": true,
    "enospc_recover_ok": true,
    "scrub_s": null,
    "scrub_found": null,
    "scrub_repaired": null,
    "data_intact": null
  }
}
