{
  "fs": "zfs",
  "layout": "mirror-enc",
  "kernel": "7.0.0-1007-azure",
  "version": "zfs-2.4.1-1ubuntu5 zfs-kmod-2.4.1-1ubuntu5",
  "date": "2026-07-14T07:16:24Z",
  "devices": "loop",
  "ndev": 4,
  "calibration": {
    "seqwrite_mbps": 408.13072872161865,
    "randwrite_iops": 14621.810672
  },
  "results": {
    "seqwrite_mbps": 188.25259590148926,
    "randwrite_iops": 1681.398611,
    "fsync_p99_ms": 191.889408,
    "fsync_p999_ms": 346.03008,
    "randread_iops": 12762.609542,
    "randread4_iops": 23108.603667,
    "seqread_mbps": 1646.9784336090088,
    "lat_idle_p99_ms": 2.408448,
    "lat_load_p99_ms": 1451.229184,
    "lat_load_max_ms": 1450.239676,
    "lat_load_ops": 10,
    "smalltree_create_ms": 2040,
    "smalltree_cp_ms": 1914,
    "smalltree_rm_ms": 868,
    "aging_mbps": [
      9.619719505310059,
      6.871376037597656,
      6.920414924621582,
      6.039444923400879,
      6.707188606262207,
      6.508694648742676,
      6.275124549865723,
      6.422477722167969,
      6.184769630432129,
      5.741970062255859
    ],
    "snapshot_create_ms": 293,
    "snapshot_delete_ms": 368,
    "reclaim_s": 13,
    "reclaim_write_mbps": 5.027098655700684,
    "compress_ratio": 3.87,
    "compress_write_mbps": 406.42984676361084,
    "reflink_ms": null,
    "divergence_plain_mbps": 7.277688980102539,
    "divergence_clone_mbps": null,
    "divergence_snap_mbps": 6.243292808532715,
    "degraded_randwrite_iops": 2023.499217,
    "degraded_randread_iops": 39780.607313,
    "rebuild_s": 22,
    "snapscale_count": 500,
    "snapscale_create_ms": 19,
    "snapscale_total_s": 9,
    "snapscale_list_ms": 237,
    "snapscale_remount_ms": 1303,
    "snapscale_delete_ms": 2643,
    "nearfull95_write_mbps": 6.211782455444336,
    "nearfull99_write_mbps": 0,
    "nearfull95_pct": 1,
    "nearfull99_pct": 100,
    "enospc_delete_ok": true,
    "enospc_recover_ok": true,
    "scrub_s": 51,
    "scrub_found": 6118,
    "scrub_repaired": 6118,
    "data_intact": true
  }
}
